Workbook

Sheet Read Me
B2: Judgment Content Analysis · Dataset template
B4: How to use this file
B5: 1. Fill the Team sheet.
B6: 2. In the Data sheet, enter one row per judgment starting at row 6. Row 5 is a made-up example showing the format; leave it as it is.
B7: 3. Pale yellow cells are yours to fill. Dropdown columns accept only the listed values (see the Vocabularies sheet). Do not add, delete or reorder columns.
B8: 4. When done, rename this file data.xlsx. Also save the Data sheet as data.csv (File > Save As > CSV). Upload both to your GitHub repository.
B9: 5. Read the Option 2 Guide for the column meanings, the charts, GitHub steps and the README.

Sheet Team
B2: Team information
B4: Topic | C4: Doctrine of promissory estoppel
B5: Court | C5: Supreme Court of India
B6: Team name | C6: The Promise Keepers
B7: GitHub repository link | C7: https://github.com/nehakaranam1234/promissory-estoppel-judgments-
B8: Member 1 · name and section | C8: Neha Karanam (23010421084), Section B
B9: Member 2 · name and section | C9: Nabaparna Kumar (23010421097), Section B
B10: Member 3 · name and section (if any) | C10: Ayushi Shahi (23010421077), Section B
B11: Member 4 · name and section (if any) | C11: Shubhra Singh (23010421115), Section B
B12: Date completed (DD-MM-YYYY) | C12: 30-10-2026

Sheet Data
A1: Data · one row per judgment
A2: Row 5 is a made-up example. Your judgments start at row 6. Enter 10 to 20 judgments decided between 01-09-2021 and 31-08-2026. See the Option 2 Guide, section 4.
A4: # | B4: Case name | C4: Citation or case number | D4: Date of decision (DD-MM-YYYY) | E4: Year | F4: Bench strength | G4: Type of case | H4: Who brought the case | I4: Outcome | J4: Who won | K4: Main provision | L4: Issue in one line | M4: Holding in one line | N4: Precedent chiefly relied on | O4: Source link (official copy) | P4: Coded by
A5: EX | B5: Example Petitioner v. State of Maharashtra (made-up) | C5: 2024 INSC 000 (made-up) | D5: 15-03-2024 | E5: 2024 | F5: 2 | G5: Criminal appeal | H5: Individual | I5: Allowed | J5: Individual | K5: s 438 CrPC | L5: Whether anticipatory bail can be limited to a fixed period. | M5: Bail granted; protection ordinarily lasts till the end of trial. | N5: Sushila Aggarwal v. State (NCT of Delhi) | O5: https://www.sci.gov.in/judgements/ (made-up) | P5: A. Deshmukh
A6: 1 | B6: Augustan Textile Colours Ltd. (now Augustan Textile Colours Pvt. Ltd.) v. Director of Industries & Anr. | C6: (2022) 6 SCC 626; 2022 INSC 408; Civil Appeal No. 2830 of 2022 | D6: 08-04-2022 | E6: 2022 | F6: 2 | G6: Civil appeal | H6: Company | I6: Dismissed | J6: State or public body | K6: s 10(1), 10(3) KGST Act 1963; s 19(3) SICA 1985 | L6: Could a sick unit's tax exemption be withdrawn, or was it protected by promissory estoppel? | M6: Dismissed: single-unit exemption was beyond s 10(1); no PE against statute (paras 27 to 31). | N6: Motilal Padampat Sugar Mills Co. Ltd. v. State of U.P. (1979) 2 SCC 409 (para 28) | O6: https://api.sci.gov.in/supremecourt/2018/26881/26881_2018_10_1501_34827_Judgement_08-Apr-2022.pdf | P6: Neha Karanam
A7: 2 | B7: Chowgule & Company Ltd. v. Assistant Director General of Foreign Trade & Ors. | C7: (2023) 1 SCC 320; Civil Appeal No. 8225 of 2009 | D7: 04-11-2022 | E7: 2022 | F7: 2 | G7: Civil appeal | H7: Company | I7: Dismissed | J7: State or public body | K7: Appendix 12, Exim Policy 1990-93 | L7: Could an exporter claim an additional licence under the old export policy after the policy changed? | M7: Dismissed: incentive is policy the Union can change; no PE, no parity claim (paras 5 to 8). | N7: No precedent on promissory estoppel applied by the Court; appellant relied on Motilal Padampat Sugar Mills Co. Ltd. v. State of U.P. (1979) 2 SCC 409 | O7: https://api.sci.gov.in/supremecourt/2008/22690/22690_2008_6_1505_39466_Judgement_04-Nov-2022.pdf | P7: Neha Karanam
A8: 3 | B8: Union of India & Ors. v. A.B.P. Pvt. Ltd. & Anr. | C8: (2023) 20 SCC 343; 2023 INSC 525; Civil Appeal No. 986 of 2011 | D8: 12-05-2023 | E8: 2023 | F8: 2 | G8: Civil appeal | H8: State or public body | I8: Allowed | J8: State or public body | K8: s 25(1) Customs Act 1962 (Notifications 86 and 164 of 2003) | L8: Could the Union withdraw a 5% customs duty concession after the importer had opened a letter of credit? | M8: Allowed: amendment valid; no PE against legislative power or vested right in a concession (paras 26 to 29). | N8: Prashanti Medical Services & Research Foundation v. Union of India (2019) 9 SCR 828 (para 26) | O8: https://api.sci.gov.in/supremecourt/2009/36138/36138_2009_12_1501_44456_Judgement_12-May-2023.pdf | P8: Neha Karanam
A9: 4 | B9: State of Gujarat v. Arcelor Mittal Nippon Steel India Ltd. | C9: (2022) 6 SCC 459; Civil Appeal Nos. 7710-7714 of 2021 | D9: 21-01-2022 | E9: 2022 | F9: 2 | G9: Civil appeal | H9: State or public body | I9: Allowed | J9: State or public body | K9: Entry 255(2), Notification of 05-03-1992 (s 49(2) Gujarat Sales Tax Act 1969) | L9: Was purchase tax payable after the unit passed gas to a power company, despite promissory estoppel? | M9: Allowed: conditions breached; PE cannot alter exemption terms or override statute (paras 19 to 22). | N9: Commissioner of Central Excise, Bangalore-I v. Bal Pharma Ltd. (2011) 2 SCC 620 (para 20.3) | O9: https://main.sci.gov.in/supremecourt/2016/28652/28652_2016_42_1501_32738_Judgement_21-Jan-2022.pdf | P9: Neha Karanam
A10: 5 | B10: Dr. Prakasan M.P. & Ors. v. State of Kerala & Anr. | C10: (2024) 20 SCC 694; 2023 INSC 772; Civil Appeal No. 7580 of 2012 | D10: 25-08-2023 | E10: 2023 | F10: 2 | G10: Civil appeal | H10: Individual | I10: Dismissed | J10: State or public body | K10: Rule 60(c) Kerala Service Rules 1958 | L10: Could teachers who retired earlier claim the later, higher retirement age on legitimate expectation or estoppel? | M10: Dismissed: retirement age is policy; no vested right, so PE and legitimate expectation fail (paras 11, 17 to 19). | N10: New Okhla Industrial Development Authority v. B.D. Singhal (2021 SCC OnLine SC 466) (paras 12 and 18) | O10: https://api.sci.gov.in/supremecourt/2010/38351/38351_2010_14_1501_46433_Judgement_25-Aug-2023.pdf | P10: Neha Karanam
A11: 6 | B11: State of Himachal Pradesh v. M/s Kundlas Loh Udyog | C11: 2026 INSC 534; Civil Appeal arising out of SLP (C) No. 26731 of 2025 | D11: 25-05-2026 | E11: 2026 | F11: 2 | G11: Civil appeal | H11: State or public body | I11: Allowed | J11: State or public body | K11: Clauses 16(a) and 16(b), Himachal Pradesh Industrial Policy 2019 | L11: Could an expanding existing unit claim the concessional power tariff meant for new units? | M11: Allowed: expansion units get only the expansion benefit; PE cannot create an entitlement the policy never gave. | N11: IFGL Refractories Ltd. v. Orissa State Financial Corporation, 2026 INSC 18 | O11: https://api.sci.gov.in/supremecourt/2025/46725/46725_2025_7_1501_71589_Judgement_25-May-2026.pdf | P11: Nabaparna Kumar
A12: 7 | B12: IFGL Refractories Ltd. v. Orissa State Financial Corporation | C12: 2026 INSC 18; 2026 SCC OnLine SC 28; Civil Appeal No. 66 of 2026 | D12: 06-01-2026 | E12: 2026 | F12: 2 | G12: Civil appeal | H12: Company | I12: Allowed | J12: Company | K12: Clauses 4.1, 5.1 and 11.4.4, Industrial Policy of Orissa 1989 | L12: Was IFGL entitled to the sanctioned subsidies for its new plant despite the claimed subsidy limit? | M12: Allowed: the new plant qualified as a new unit; sanctioned subsidies payable with 9% interest. | N12: Motilal Padampat Sugar Mills Co. Ltd. v. State of U.P. (1979) 2 SCC 409 | P12: Nabaparna Kumar
A13: 8 | B13: Puja Ferro Alloys Pvt. Ltd. v. State of Goa | C13: 2025 INSC 217; Civil Appeal Nos. 2027-2028 of 2012 | D13: 14-02-2025 | E13: 2025 | G13: Civil appeal | H13: Company | I13: Dismissed | J13: State or public body | K13: Goa (Prohibition of Further Payments and Recovery of Rebate Benefits) Act 2002 | L13: Could the companies keep the 25% power rebate after the State withdrew it and sought recovery? | M13: Dismissed: claim barred by res judicata; promissory estoppel yields to overriding public interest. | N13: G.R. Ispat Ltd. v. Chief Electrical Engineer, 1999 (1) Goa L.T. | O13: https://api.sci.gov.in/supremecourt/2012/1038/1038_2012_14_1501_59452_Judgement_14-Feb-2025.pdf | P13: Nabaparna Kumar
A14: 9 | B14: Satish Chander Sharma & Ors. v. State of Himachal Pradesh & Ors. | C14: 2025 INSC 491; Writ Petition (Civil) No. 179 of 2018 | D14: 16-04-2025 | E14: 2025 | F14: 3 | G14: Writ petition | H14: Individual | I14: Dismissed | J14: State or public body | K14: Article 32, Constitution of India; HP Corporate Sector Employees Pension Scheme 1999 | L14: Could retired corporation employees claim pension under the 1999 Scheme after its 2004 withdrawal? | M14: Dismissed: Article 32 cannot reopen a final judgment; no promissory estoppel as PF rights were restored. | N14: State of Himachal Pradesh v. Rajesh Chander Sood (2016) 10 SCC 77 | O14: https://api.sci.gov.in/supremecourt/2018/6546/6546_2018_3_1501_60931_Judgement_16-Apr-2025.pdf | P14: Nabaparna Kumar
A15: 10 | B15: M/s Rewa Tollway Pvt. Ltd. v. State of Madhya Pradesh & Ors. | C15: 2024 INSC 539 | D15: 19-07-2024 | E15: 2024 | F15: 2 | G15: Civil appeal | H15: Company | I15: Partly allowed | J15: Mixed or unclear | K15: Proviso (c) to clause (C), Article 33, Schedule 1-A, Indian Stamp Act 1899 | L15: Could the State charge higher stamp duty under a 2002 amendment despite an earlier Rs 100 stamp-paper assurance? | M15: Partly allowed: no promissory estoppel against legislative power; public interest overrides executive assurance. | N15: Hero Motocorp Ltd. v. Union of India (2022) | O15: https://api.sci.gov.in/supremecourt/2010/14397/14397_2010_7_1501_53819_Judgement_19-Jul-2024.pdf | P15: Shubhra Singh
A16: 11 | B16: Hero Motocorp Ltd. v. Union of India & Ors. | C16: 2022 INSC 1100 | D16: 17-10-2022 | E16: 2022 | F16: 2 | G16: Civil appeal | H16: Company | I16: Dismissed | J16: State or public body | K16: Proviso to s 174(2)(c), CGST Act 2017 | L16: Could the Union be held to its 2003 promise of 10 years' excise exemption after GST replaced the excise regime? | M16: Dismissed: no promissory estoppel against legislative power; the GST Act ended the exemption. | N16: M. Ramanatha Pillai v. State of Kerala (1973) | O16: https://indiankanoon.org/doc/179484826/ | P16: Shubhra Singh
A17: 12 | B17: State of West Bengal & Ors. v. Gitashree Dutta (Dey) | C17: (2022) 19 SCC 388; Civil Appeal No. 4254 of 2022 | D17: 20-04-2022 | E17: 2022 | F17: 2 | G17: Civil appeal | H17: State or public body | I17: Allowed | J17: State or public body | K17: s 12, National Food Security Act 2013 | L17: Could the State cancel declared fair price shop vacancies to implement the Food Security Act? | M17: Allowed: no estoppel against a statute; applicant in an unfinalised selection had no vested right (paras 25 to 29). | N17: A.P. Dairy Development Corpn. Federation v. B. Narasimha Reddy (2011) 9 SCC 286 (para 27) | O17: https://api.sci.gov.in/supremecourt/2019/43716/43716_2019_7_9_35128_Judgement_20-Apr-2022.pdf | P17: Shubhra Singh
A18: 13 | B18: Yamuna Expressway Industrial Development Authority & Ors. v. Shakuntala Education and Welfare Society & Ors. | C18: (2022) 20 SCC 698 | D18: 19-05-2022 | E18: 2022 | F18: 2 | G18: Civil appeal | H18: State or public body | I18: Allowed | J18: State or public body | K18: Articles 14 and 300A, Constitution of India | L18: Could allottees hold YEIDA to the premium in their leases against a later policy demanding extra payment? | M18: Allowed: no promissory estoppel; policy change in public interest prevails. | N18: Kasinka Trading v. Union of India | O18: https://indiankanoon.org/doc/45288368/ | P18: Shubhra Singh
A19: 14 | B19: State of Maharashtra & Ors. v. Reliance Industries Ltd. & Ors. | C19: 2026 INSC 296; Civil Appeal Nos. 3012-3026 of 2010 | D19: 25-03-2026 | E19: 2026 | F19: 2 | G19: Civil appeal | H19: State or public body | I19: Allowed | J19: State or public body | K19: s 5A, Bombay Electricity Duty Act 1958 | L19: Could the State withdraw a captive-power electricity duty exemption despite promissory estoppel and legitimate expectation? | M19: Allowed: power to exempt includes power to withdraw; no vested right; reasonable notice needed. | N19: Shrijee Sales Corporation v. Union of India (1997) | O19: https://indiankanoon.org/doc/170515926/ | P19: Shubhra Singh
A20: 15 | B20: State of Uttar Pradesh & Ors. v. Principal Abhay Nandan Inter College & Ors. | C20: (2021) 15 SCC 600; 2021 INSC 551; Civil Appeal No. 865 of 2021 | D20: 27-09-2021 | E20: 2021 | F20: 2 | G20: Civil appeal | H20: State or public body | I20: Allowed | J20: State or public body | K20: Regulation 101, Intermediate Education Act 1921 | L20: Could the State require aided colleges to outsource Class IV staff, or was it barred by estoppel? | M20: Allowed: aid is not a fundamental right; the State may attach conditions (paras 29 to 30). | N20: T.M.A. Pai Foundation v. State of Karnataka (2002) 8 SCC 481 | O20: https://api.sci.gov.in/supremecourt/2019/18529/18529_2019_36_1502_30326_Judgement_27-Sep-2021.pdf | P20: Ayushi Shahi
A21: 16 | B21: The Vice Chairman & Managing Director, City and Industrial Development Corporation of Maharashtra Ltd. & Anr. v. Shishir Realty Private Limited & Ors. | C21: 2021 INSC 796; Civil Appeal Nos. 3956-3957 of 2017 | D21: 29-11-2021 | E21: 2021 | F21: 3 | G21: Civil appeal | H21: State or public body | I21: Dismissed | J21: Company | K21: Article 14, Constitution of India; Maharashtra Regional and Town Planning Act 1966 | L21: Could CIDCO cancel an allotment and lease deeds without proof of a violation or a pressing public interest? | M21: Dismissed: cancellation unjustified; promissory estoppel can bind the State and yields only to proven public interest. | N21: Motilal Padampat Sugar Mills Co. Ltd. v. State of U.P. (1979) 2 SCC 409 | O21: https://indiankanoon.org/doc/74190276/ | P21: Ayushi Shahi
A22: 17 | B22: Directorate of Film Festivals & Ors. v. Gaurav Ashok Ailani & Ors. | C22: (2022) 12 SCC 341 | D22: 15-03-2022 | E22: 2022 | F22: 2 | G22: Civil appeal | H22: State or public body | I22: Allowed | J22: State or public body | K22: Article 14 of Constitution of India / Administrative Eligibility Regulations | L22: Whether public authorities are estoppel-bound to retain existing criteria for public benefits and awards without modification. | M22: Administrative eligibility criteria can be altered midway for administrative feasibility; no absolute rights exist under promissory estoppel. | N22: State of Jharkhand v. Brahmputra Metallics Ltd. (2020) | O22: https://indiankanoon.org/doc/1014138 | P22: Ayushi Shahi
A23: 18 | B23: State of Punjab & Ors. v. Amrit Vanaspati Co. Ltd. | C23: (2022) 7 SCC 592 | D23: 19-05-2022 | E23: 2022 | F23: 2 | G23: Civil appeal | H23: State or public body | I23: Allowed | J23: State or public body | K23: Punjab General Sales Tax Act / Industrial Tax Concession Notification | L23: Whether tax exemptions promised via executive press notes can bind the State when the formal statutory notification contains explicit limitations. | M23: No promissory estoppel can lie against the State to enforce an executive concession that contradicts or exceeds the boundaries set by the parent statute and formal notification. | N23: Kasinka Trading v. Union of India (1995) | O23: https://indiankanoon.org/doc/208331/ | P23: Ayushi Shahi
A24: 19
A25: 20

Sheet Chart counts
A1: Counts for your charts (these update automatically from the Data sheet)
A2: Select a table below, then Insert > Chart in Excel or Google Sheets. Save each chart as PNG.
A4: Year | B4: Judgments
A5: 2021 | B5: =COUNTIF(Data!E$6:E$25,A5) -> 2
A6: 2022 | B6: =COUNTIF(Data!E$6:E$25,A6) -> 8
A7: 2023 | B7: =COUNTIF(Data!E$6:E$25,A7) -> 2
A8: 2024 | B8: =COUNTIF(Data!E$6:E$25,A8) -> 1
A9: 2025 | B9: =COUNTIF(Data!E$6:E$25,A9) -> 2
A10: 2026 | B10: =COUNTIF(Data!E$6:E$25,A10) -> 3
A12: Outcome | B12: Judgments
A13: Allowed | B13: =COUNTIF(Data!I$6:I$25,A13) -> 10
A14: Dismissed | B14: =COUNTIF(Data!I$6:I$25,A14) -> 7
A15: Partly allowed | B15: =COUNTIF(Data!I$6:I$25,A15) -> 1
A16: Other | B16: =COUNTIF(Data!I$6:I$25,A16) -> 0
A18: Who brought the case | B18: Judgments
A19: Individual | B19: =COUNTIF(Data!H$6:H$25,A19) -> 2
A20: Company | B20: =COUNTIF(Data!H$6:H$25,A20) -> 6
A21: State or public body | B21: =COUNTIF(Data!H$6:H$25,A21) -> 10
A22: Association or NGO | B22: =COUNTIF(Data!H$6:H$25,A22) -> 0
A23: Other | B23: =COUNTIF(Data!H$6:H$25,A23) -> 0
A25: Who won | B25: Judgments
A26: Individual | B26: =COUNTIF(Data!J$6:J$25,A26) -> 0
A27: Company | B27: =COUNTIF(Data!J$6:J$25,A27) -> 2
A28: State or public body | B28: =COUNTIF(Data!J$6:J$25,A28) -> 15
A29: Association or NGO | B29: =COUNTIF(Data!J$6:J$25,A29) -> 0
A30: Mixed or unclear | B30: =COUNTIF(Data!J$6:J$25,A30) -> 1
A32: Type of case | B32: Judgments
A33: Writ petition | B33: =COUNTIF(Data!G$6:G$25,A33) -> 1
A34: Civil appeal | B34: =COUNTIF(Data!G$6:G$25,A34) -> 17
A35: Criminal appeal | B35: =COUNTIF(Data!G$6:G$25,A35) -> 0
A36: SLP | B36: =COUNTIF(Data!G$6:G$25,A36) -> 0
A37: Other | B37: =COUNTIF(Data!G$6:G$25,A37) -> 0

Sheet Vocabularies
A1: Lists used by the dropdowns (do not edit)
A2: Type of case | B2: Who brought the case | C2: Outcome | D2: Who won
A3: Writ petition | B3: Individual | C3: Allowed | D3: Individual
A4: Civil appeal | B4: Company | C4: Dismissed | D4: Company
A5: Criminal appeal | B5: State or public body | C5: Partly allowed | D5: State or public body
A6: SLP | B6: Association or NGO | C6: Other | D6: Association or NGO
A7: Other | B7: Other | D7: Mixed or unclear
